{
"meta":{"test_sets":[],"test_metrics":[],"learn_metrics":[{"best_value":"Min","name":"Poisson"}],"launch_mode":"Train","parameters":"","iteration_count":600,"learn_sets":["learn"],"name":"experiment"},
"iterations":[
{"learn":[0.9868886746],"iteration":0,"passed_time":0.007334437364,"remaining_time":4.393327981},
{"learn":[0.9732145076],"iteration":1,"passed_time":0.0128406485,"remaining_time":3.839353902},
{"learn":[0.961001693],"iteration":2,"passed_time":0.01814533639,"remaining_time":3.610921942},
{"learn":[0.9510184745],"iteration":3,"passed_time":0.02265635358,"remaining_time":3.375796683},
{"learn":[0.9408485061],"iteration":4,"passed_time":0.02751965494,"remaining_time":3.274838938},
{"learn":[0.9318078919],"iteration":5,"passed_time":0.03246499635,"remaining_time":3.214034639},
{"learn":[0.9232071716],"iteration":6,"passed_time":0.03729148537,"remaining_time":3.159121547},
{"learn":[0.9161610004],"iteration":7,"passed_time":0.04163239539,"remaining_time":3.080797259},
{"learn":[0.9091506725],"iteration":8,"passed_time":0.04672822192,"remaining_time":3.068486573},
{"learn":[0.9022935798],"iteration":9,"passed_time":0.05106244949,"remaining_time":3.01268452},
{"learn":[0.8956357127],"iteration":10,"passed_time":0.05585118354,"remaining_time":2.99057701},
{"learn":[0.8901327879],"iteration":11,"passed_time":0.06042579802,"remaining_time":2.960864103},
{"learn":[0.8848636168],"iteration":12,"passed_time":0.06508568602,"remaining_time":2.938869053},
{"learn":[0.8797518165],"iteration":13,"passed_time":0.06970655801,"remaining_time":2.917717357},
{"learn":[0.8754395885],"iteration":14,"passed_time":0.07422218202,"remaining_time":2.894665099},
{"learn":[0.871378467],"iteration":15,"passed_time":0.07950664822,"remaining_time":2.90199266},
{"learn":[0.8665798556],"iteration":16,"passed_time":0.08523044877,"remaining_time":2.922903037},
{"learn":[0.8625707017],"iteration":17,"passed_time":0.09164158823,"remaining_time":2.96307802},
{"learn":[0.8588584397],"iteration":18,"passed_time":0.09643662945,"remaining_time":2.948930616},
{"learn":[0.8552318902],"iteration":19,"passed_time":0.1010589914,"remaining_time":2.930710751},
{"learn":[0.8518991939],"iteration":20,"passed_time":0.1075004091,"remaining_time":2.963939851},
{"learn":[0.8491817196],"iteration":21,"passed_time":0.1129930927,"remaining_time":2.968636709},
{"learn":[0.8460638317],"iteration":22,"passed_time":0.1180550251,"remaining_time":2.961641282},
{"learn":[0.8431969286],"iteration":23,"passed_time":0.1248057678,"remaining_time":2.995338428},
{"learn":[0.8407063207],"iteration":24,"passed_time":0.1303739342,"remaining_time":2.998600487},
{"learn":[0.8381872058],"iteration":25,"passed_time":0.1349414633,"remaining_time":2.979092304},
{"learn":[0.836047482],"iteration":26,"passed_time":0.1414236476,"remaining_time":3.001324077},
{"learn":[0.8339376796],"iteration":27,"passed_time":0.1463369761,"remaining_time":2.98945537},
{"learn":[0.8315831019],"iteration":28,"passed_time":0.1505272493,"remaining_time":2.963829632},
{"learn":[0.8292013925],"iteration":29,"passed_time":0.1555458175,"remaining_time":2.955370532},
{"learn":[0.826917878],"iteration":30,"passed_time":0.1600722155,"remaining_time":2.938099697},
{"learn":[0.8251045593],"iteration":31,"passed_time":0.1646229023,"remaining_time":2.922056516},
{"learn":[0.8231238283],"iteration":32,"passed_time":0.1701127232,"remaining_time":2.92284588},
{"learn":[0.8215091642],"iteration":33,"passed_time":0.1750356764,"remaining_time":2.913829201},
{"learn":[0.8198933675],"iteration":34,"passed_time":0.1796100719,"remaining_time":2.899419732},
{"learn":[0.8182778899],"iteration":35,"passed_time":0.1848476532,"remaining_time":2.895946567},
{"learn":[0.8169035974],"iteration":36,"passed_time":0.1895227256,"remaining_time":2.883818771},
{"learn":[0.8151966968],"iteration":37,"passed_time":0.194088538,"remaining_time":2.870467326},
{"learn":[0.8137005096],"iteration":38,"passed_time":0.1985758617,"remaining_time":2.856437395},
{"learn":[0.8124973763],"iteration":39,"passed_time":0.2033125067,"remaining_time":2.846375093},
{"learn":[0.8114060151],"iteration":40,"passed_time":0.2078287397,"remaining_time":2.833567452},
{"learn":[0.8103111066],"iteration":41,"passed_time":0.2123434717,"remaining_time":2.821134696},
{"learn":[0.8092320004],"iteration":42,"passed_time":0.217532314,"remaining_time":2.8178023},
{"learn":[0.8083802047],"iteration":43,"passed_time":0.2225776732,"remaining_time":2.812572416},
{"learn":[0.8074384435],"iteration":44,"passed_time":0.2276020236,"remaining_time":2.807091624},
{"learn":[0.806782839],"iteration":45,"passed_time":0.232708334,"remaining_time":2.802617761},
{"learn":[0.8058013675],"iteration":46,"passed_time":0.2376495038,"remaining_time":2.796173949},
{"learn":[0.8050426017],"iteration":47,"passed_time":0.2422921332,"remaining_time":2.786359532},
{"learn":[0.8042677522],"iteration":48,"passed_time":0.2470123073,"remaining_time":2.77762819},
{"learn":[0.8034586118],"iteration":49,"passed_time":0.2516876061,"remaining_time":2.768563667},
{"learn":[0.8028148627],"iteration":50,"passed_time":0.2563284497,"remaining_time":2.75930037},
{"learn":[0.8023129374],"iteration":51,"passed_time":0.2603447808,"remaining_time":2.743633459},
{"learn":[0.8015983407],"iteration":52,"passed_time":0.2653401014,"remaining_time":2.738510103},
{"learn":[0.8010181987],"iteration":53,"passed_time":0.2702070592,"remaining_time":2.732093599},
{"learn":[0.8003675208],"iteration":54,"passed_time":0.2747401096,"remaining_time":2.722424723},
{"learn":[0.7996239401],"iteration":55,"passed_time":0.279772972,"remaining_time":2.717794585},
{"learn":[0.7991385353],"iteration":56,"passed_time":0.2846124057,"remaining_time":2.711307655},
{"learn":[0.798597381],"iteration":57,"passed_time":0.2892207637,"remaining_time":2.702718171},
{"learn":[0.7980167709],"iteration":58,"passed_time":0.2941089842,"remaining_time":2.696829838},
{"learn":[0.7974932336],"iteration":59,"passed_time":0.298528513,"remaining_time":2.686756617},
{"learn":[0.7968562176],"iteration":60,"passed_time":0.3032926781,"remaining_time":2.679913991},
{"learn":[0.7964586016],"iteration":61,"passed_time":0.3076829562,"remaining_time":2.669894039},
{"learn":[0.7960055483],"iteration":62,"passed_time":0.3126095155,"remaining_time":2.664623966},
{"learn":[0.7954931633],"iteration":63,"passed_time":0.3173099524,"remaining_time":2.657470851},
{"learn":[0.7950823314],"iteration":64,"passed_time":0.3227143691,"remaining_time":2.6561875},
{"learn":[0.7946280343],"iteration":65,"passed_time":0.3274213832,"remaining_time":2.649136646},
{"learn":[0.7941789976],"iteration":66,"passed_time":0.3323133079,"remaining_time":2.643626763},
{"learn":[0.7937108859],"iteration":67,"passed_time":0.3370069271,"remaining_time":2.636583606},
{"learn":[0.7932185145],"iteration":68,"passed_time":0.341576248,"remaining_time":2.628651995},
{"learn":[0.7926418335],"iteration":69,"passed_time":0.3462222697,"remaining_time":2.621397185},
{"learn":[0.7920332674],"iteration":70,"passed_time":0.351051681,"remaining_time":2.615582243},
{"learn":[0.7917509473],"iteration":71,"passed_time":0.3559224396,"remaining_time":2.610097891},
{"learn":[0.7913029005],"iteration":72,"passed_time":0.3605168185,"remaining_time":2.602635114},
{"learn":[0.790966394],"iteration":73,"passed_time":0.3652077456,"remaining_time":2.595936137},
{"learn":[0.7904937155],"iteration":74,"passed_time":0.3701341283,"remaining_time":2.590938898},
{"learn":[0.7900361357],"iteration":75,"passed_time":0.3751656942,"remaining_time":2.586668734},
{"learn":[0.7893692908],"iteration":76,"passed_time":0.3797785038,"remaining_time":2.579534513},
{"learn":[0.788916677],"iteration":77,"passed_time":0.384332559,"remaining_time":2.572071741},
{"learn":[0.7886814653],"iteration":78,"passed_time":0.3889774721,"remaining_time":2.56528181},
{"learn":[0.788298173],"iteration":79,"passed_time":0.3936078081,"remaining_time":2.558450753},
{"learn":[0.7878612554],"iteration":80,"passed_time":0.3984470418,"remaining_time":2.553012527},
{"learn":[0.7874683813],"iteration":81,"passed_time":0.4038164377,"remaining_time":2.550937985},
{"learn":[0.7872314488],"iteration":82,"passed_time":0.4090985133,"remaining_time":2.548240137},
{"learn":[0.7868562126],"iteration":83,"passed_time":0.4150653089,"remaining_time":2.549686897},
{"learn":[0.786600779],"iteration":84,"passed_time":0.4204692483,"remaining_time":2.547548975},
{"learn":[0.7862733995],"iteration":85,"passed_time":0.4260636263,"remaining_time":2.546473301},
{"learn":[0.7860766152],"iteration":86,"passed_time":0.4318993238,"remaining_time":2.546716702},
{"learn":[0.7857846273],"iteration":87,"passed_time":0.4388083856,"remaining_time":2.553066971},
{"learn":[0.7854417704],"iteration":88,"passed_time":0.4461322483,"remaining_time":2.561500886},
{"learn":[0.7850589571],"iteration":89,"passed_time":0.4553055884,"remaining_time":2.580065001},
{"learn":[0.7848155694],"iteration":90,"passed_time":0.4616105278,"remaining_time":2.58197537},
{"learn":[0.7844435183],"iteration":91,"passed_time":0.4680284186,"remaining_time":2.584330833},
{"learn":[0.7839783269],"iteration":92,"passed_time":0.4730626825,"remaining_time":2.578954624},
{"learn":[0.7836789188],"iteration":93,"passed_time":0.4779969788,"remaining_time":2.573047567},
{"learn":[0.7834530691],"iteration":94,"passed_time":0.4834482838,"remaining_time":2.569909298},
{"learn":[0.7830920193],"iteration":95,"passed_time":0.4883150164,"remaining_time":2.563653836},
{"learn":[0.7827998052],"iteration":96,"passed_time":0.4930825856,"remaining_time":2.556912789},
{"learn":[0.7825708117],"iteration":97,"passed_time":0.4981646159,"remaining_time":2.551822828},
{"learn":[0.7824368025],"iteration":98,"passed_time":0.5028216829,"remaining_time":2.544582456},
{"learn":[0.7821803815],"iteration":99,"passed_time":0.5080140948,"remaining_time":2.540070474},
{"learn":[0.7820298535],"iteration":100,"passed_time":0.5125423734,"remaining_time":2.532263805},
{"learn":[0.7817286901],"iteration":101,"passed_time":0.5174173291,"remaining_time":2.526214018},
{"learn":[0.781556216],"iteration":102,"passed_time":0.5221201016,"remaining_time":2.519356218},
{"learn":[0.7811515216],"iteration":103,"passed_time":0.5268458097,"remaining_time":2.512649246},
{"learn":[0.7808107274],"iteration":104,"passed_time":0.5316238899,"remaining_time":2.506226909},
{"learn":[0.7804680671],"iteration":105,"passed_time":0.5361359526,"remaining_time":2.498595854},
{"learn":[0.7802389696],"iteration":106,"passed_time":0.5408157167,"remaining_time":2.491795779},
{"learn":[0.7800583099],"iteration":107,"passed_time":0.545305214,"remaining_time":2.484168197},
{"learn":[0.7798210825],"iteration":108,"passed_time":0.5497723103,"remaining_time":2.476497287},
{"learn":[0.7794709243],"iteration":109,"passed_time":0.5550365456,"remaining_time":2.472435521},
{"learn":[0.7792067343],"iteration":110,"passed_time":0.5601942777,"remaining_time":2.467882899},
{"learn":[0.7789006553],"iteration":111,"passed_time":0.5655041826,"remaining_time":2.46398251},
{"learn":[0.778672166],"iteration":112,"passed_time":0.57052035,"remaining_time":2.458791243},
{"learn":[0.7784773603],"iteration":113,"passed_time":0.5749345668,"remaining_time":2.451036838},
{"learn":[0.7780149456],"iteration":114,"passed_time":0.5798394334,"remaining_time":2.445409784},
{"learn":[0.7777217976],"iteration":115,"passed_time":0.5845120721,"remaining_time":2.438826232},
{"learn":[0.7775455904],"iteration":116,"passed_time":0.5889869612,"remaining_time":2.431458994},
{"learn":[0.7773712168],"iteration":117,"passed_time":0.5935553345,"remaining_time":2.424522638},
{"learn":[0.7770789387],"iteration":118,"passed_time":0.5987258413,"remaining_time":2.420059913},
{"learn":[0.7768807679],"iteration":119,"passed_time":0.6048437422,"remaining_time":2.419374969},
{"learn":[0.7767606083],"iteration":120,"passed_time":0.6102402388,"remaining_time":2.415744417},
{"learn":[0.7766130298],"iteration":121,"passed_time":0.6158155281,"remaining_time":2.41278543},
{"learn":[0.7761751442],"iteration":122,"passed_time":0.6215270102,"remaining_time":2.410312064},
{"learn":[0.775883069],"iteration":123,"passed_time":0.6262402946,"remaining_time":2.403954679},
{"learn":[0.7757001608],"iteration":124,"passed_time":0.6310379768,"remaining_time":2.397944312},
{"learn":[0.7754549499],"iteration":125,"passed_time":0.635338532,"remaining_time":2.390083049},
{"learn":[0.7751989491],"iteration":126,"passed_time":0.6399077208,"remaining_time":2.383278362},
{"learn":[0.7748363318],"iteration":127,"passed_time":0.6446578095,"remaining_time":2.377175673},
{"learn":[0.7746784608],"iteration":128,"passed_time":0.6490533496,"remaining_time":2.369799439},
{"learn":[0.774296415],"iteration":129,"passed_time":0.65353195,"remaining_time":2.362769358},
{"learn":[0.7741035475],"iteration":130,"passed_time":0.6581226315,"remaining_time":2.356179498},
{"learn":[0.7738614896],"iteration":131,"passed_time":0.6630848551,"remaining_time":2.350937214},
{"learn":[0.7736854325],"iteration":132,"passed_time":0.6679242366,"remaining_time":2.345267808},
{"learn":[0.7735449493],"iteration":133,"passed_time":0.6723300915,"remaining_time":2.338103154},
{"learn":[0.7732614932],"iteration":134,"passed_time":0.6773654159,"remaining_time":2.333147544},
{"learn":[0.7731531185],"iteration":135,"passed_time":0.6823745507,"remaining_time":2.328101408},
{"learn":[0.7729077712],"iteration":136,"passed_time":0.6869523346,"remaining_time":2.321598036},
{"learn":[0.7726587476],"iteration":137,"passed_time":0.6915825434,"remaining_time":2.31529808},
{"learn":[0.7724951796],"iteration":138,"passed_time":0.6962165508,"remaining_time":2.309034748},
{"learn":[0.772213937],"iteration":139,"passed_time":0.7007826033,"remaining_time":2.302571411},
{"learn":[0.7720629114],"iteration":140,"passed_time":0.7051222629,"remaining_time":2.295398005},
{"learn":[0.771825886],"iteration":141,"passed_time":0.7098198135,"remaining_time":2.289418835},
{"learn":[0.7714661982],"iteration":142,"passed_time":0.7141609725,"remaining_time":2.282318632},
{"learn":[0.7713022889],"iteration":143,"passed_time":0.7186797759,"remaining_time":2.27581929},
{"learn":[0.7711601461],"iteration":144,"passed_time":0.7232380584,"remaining_time":2.269471149},
{"learn":[0.770955596],"iteration":145,"passed_time":0.728066726,"remaining_time":2.263988312},
{"learn":[0.7707694064],"iteration":146,"passed_time":0.7325761389,"remaining_time":2.25753055},
{"learn":[0.7706881223],"iteration":147,"passed_time":0.7370390936,"remaining_time":2.250957232},
{"learn":[0.7705529184],"iteration":148,"passed_time":0.7414195381,"remaining_time":2.244162494},
{"learn":[0.7703463631],"iteration":149,"passed_time":0.7458574736,"remaining_time":2.237572421},
{"learn":[0.7701513241],"iteration":150,"passed_time":0.7505260036,"remaining_time":2.231696527},
{"learn":[0.7699857468],"iteration":151,"passed_time":0.7552747731,"remaining_time":2.226073015},
{"learn":[0.7698007292],"iteration":152,"passed_time":0.7599830176,"remaining_time":2.220342542},
{"learn":[0.7696557233],"iteration":153,"passed_time":0.7643543288,"remaining_time":2.21364955},
{"learn":[0.7694414587],"iteration":154,"passed_time":0.7690432251,"remaining_time":2.207898291},
{"learn":[0.769191996],"iteration":155,"passed_time":0.7736223624,"remaining_time":2.201848262},
{"learn":[0.7690208298],"iteration":156,"passed_time":0.7783491849,"remaining_time":2.196233687},
{"learn":[0.7688404239],"iteration":157,"passed_time":0.7827452823,"remaining_time":2.189705157},
{"learn":[0.7686740086],"iteration":158,"passed_time":0.7879540702,"remaining_time":2.185457515},
{"learn":[0.7684032506],"iteration":159,"passed_time":0.7938027553,"remaining_time":2.182957577},
{"learn":[0.7680639153],"iteration":160,"passed_time":0.7988527451,"remaining_time":2.17823823},
{"learn":[0.767734181],"iteration":161,"passed_time":0.8036426496,"remaining_time":2.172811608},
{"learn":[0.7675860199],"iteration":162,"passed_time":0.8086109923,"remaining_time":2.167871188},
{"learn":[0.7674304241],"iteration":163,"passed_time":0.813895265,"remaining_time":2.163770339},
{"learn":[0.7672088918],"iteration":164,"passed_time":0.8185757322,"remaining_time":2.158063294},
{"learn":[0.7669965011],"iteration":165,"passed_time":0.8231725054,"remaining_time":2.152149803},
{"learn":[0.7667737463],"iteration":166,"passed_time":0.8289811507,"remaining_time":2.149394241},
{"learn":[0.7665544964],"iteration":167,"passed_time":0.834404589,"remaining_time":2.1456118},
{"learn":[0.7662225384],"iteration":168,"passed_time":0.8392405803,"remaining_time":2.140311776},
{"learn":[0.7659839838],"iteration":169,"passed_time":0.8453089914,"remaining_time":2.138134508},
{"learn":[0.7656948982],"iteration":170,"passed_time":0.8503923834,"remaining_time":2.133440541},
{"learn":[0.76555946],"iteration":171,"passed_time":0.8550458479,"remaining_time":2.127672226},
{"learn":[0.7652959812],"iteration":172,"passed_time":0.8605763165,"remaining_time":2.124081428},
{"learn":[0.7651929897],"iteration":173,"passed_time":0.8658132447,"remaining_time":2.119749668},
{"learn":[0.7649464464],"iteration":174,"passed_time":0.870983433,"remaining_time":2.11524548},
{"learn":[0.7647161821],"iteration":175,"passed_time":0.8764683721,"remaining_time":2.111491987},
{"learn":[0.7644947584],"iteration":176,"passed_time":0.8820379376,"remaining_time":2.107921173},
{"learn":[0.7643251898],"iteration":177,"passed_time":0.8875461097,"remaining_time":2.10418235},
{"learn":[0.7641180252],"iteration":178,"passed_time":0.893541725,"remaining_time":2.101570202},
{"learn":[0.7639611485],"iteration":179,"passed_time":0.898641783,"remaining_time":2.096830827},
{"learn":[0.7636456609],"iteration":180,"passed_time":0.903561261,"remaining_time":2.091669438},
{"learn":[0.7634727932],"iteration":181,"passed_time":0.9083695622,"remaining_time":2.086255368},
{"learn":[0.7633095734],"iteration":182,"passed_time":0.9129215695,"remaining_time":2.080263904},
{"learn":[0.7631676402],"iteration":183,"passed_time":0.917473937,"remaining_time":2.074288901},
{"learn":[0.7629733871],"iteration":184,"passed_time":0.9221181381,"remaining_time":2.068535283},
{"learn":[0.7627968341],"iteration":185,"passed_time":0.9267607286,"remaining_time":2.062790009},
{"learn":[0.7625199727],"iteration":186,"passed_time":0.9311922018,"remaining_time":2.056590264},
{"learn":[0.7624555304],"iteration":187,"passed_time":0.9356060474,"remaining_time":2.0503707},
{"learn":[0.7622276713],"iteration":188,"passed_time":0.9405271099,"remaining_time":2.045273239},
{"learn":[0.762029002],"iteration":189,"passed_time":0.9449564123,"remaining_time":2.039116469},
{"learn":[0.7616712711],"iteration":190,"passed_time":0.9496772575,"remaining_time":2.033602085},
{"learn":[0.7615416998],"iteration":191,"passed_time":0.9543766211,"remaining_time":2.02805032},
{"learn":[0.7612725749],"iteration":192,"passed_time":0.9591410363,"remaining_time":2.022644569},
{"learn":[0.7609097649],"iteration":193,"passed_time":0.9639777479,"remaining_time":2.01739673},
{"learn":[0.7607709902],"iteration":194,"passed_time":0.9684137827,"remaining_time":2.011320933},
{"learn":[0.7607249136],"iteration":195,"passed_time":0.9731282925,"remaining_time":2.005835868},
{"learn":[0.7604657583],"iteration":196,"passed_time":0.9777659012,"remaining_time":2.00020131},
{"learn":[0.7604359236],"iteration":197,"passed_time":0.9820521211,"remaining_time":1.993863397},
{"learn":[0.7602670593],"iteration":198,"passed_time":0.986714406,"remaining_time":1.988303904},
{"learn":[0.7602347414],"iteration":199,"passed_time":0.9911254146,"remaining_time":1.982250829},
{"learn":[0.7600638537],"iteration":200,"passed_time":0.9959242818,"remaining_time":1.976984022},
{"learn":[0.7598898734],"iteration":201,"passed_time":1.0005329,"remaining_time":1.971347},
{"learn":[0.7598053664],"iteration":202,"passed_time":1.004876861,"remaining_time":1.96520253},
{"learn":[0.7597775243],"iteration":203,"passed_time":1.009130179,"remaining_time":1.958899759},
{"learn":[0.7597050746],"iteration":204,"passed_time":1.013421471,"remaining_time":1.952690151},
{"learn":[0.7596861033],"iteration":205,"passed_time":1.017141608,"remaining_time":1.945406765},
{"learn":[0.7595871471],"iteration":206,"passed_time":1.021912291,"remaining_time":1.940152321},
{"learn":[0.7594506448],"iteration":207,"passed_time":1.027370449,"remaining_time":1.936198155},
{"learn":[0.7591100346],"iteration":208,"passed_time":1.033470464,"remaining_time":1.933430389},
{"learn":[0.7589679892],"iteration":209,"passed_time":1.039060963,"remaining_time":1.929684645},
{"learn":[0.7588014972],"iteration":210,"passed_time":1.043826575,"remaining_time":1.924400653},
{"learn":[0.7586249951],"iteration":211,"passed_time":1.048507293,"remaining_time":1.918966177},
{"learn":[0.7584673528],"iteration":212,"passed_time":1.053064292,"remaining_time":1.913313995},
{"learn":[0.7583036189],"iteration":213,"passed_time":1.05778521,"remaining_time":1.907967715},
{"learn":[0.7581207583],"iteration":214,"passed_time":1.062587907,"remaining_time":1.902773695},
{"learn":[0.7580226451],"iteration":215,"passed_time":1.066951486,"remaining_time":1.896802641},
{"learn":[0.7578319577],"iteration":216,"passed_time":1.071553904,"remaining_time":1.891267951},
{"learn":[0.7577707021],"iteration":217,"passed_time":1.075942581,"remaining_time":1.885367275},
{"learn":[0.7576342038],"iteration":218,"passed_time":1.080554508,"remaining_time":1.879868802},
{"learn":[0.7574397469],"iteration":219,"passed_time":1.084979953,"remaining_time":1.874056282},
{"learn":[0.7570522001],"iteration":220,"passed_time":1.089781521,"remaining_time":1.868901342},
{"learn":[0.7566544775],"iteration":221,"passed_time":1.094846401,"remaining_time":1.864197926},
{"learn":[0.7564424513],"iteration":222,"passed_time":1.099378911,"remaining_time":1.858591254},
{"learn":[0.7562440674],"iteration":223,"passed_time":1.104237811,"remaining_time":1.85354204},
{"learn":[0.7560571438],"iteration":224,"passed_time":1.108982123,"remaining_time":1.848303538},
{"learn":[0.7559371061],"iteration":225,"passed_time":1.113443567,"remaining_time":1.842601301},
{"learn":[0.7556959576],"iteration":226,"passed_time":1.117731128,"remaining_time":1.836624276},
{"learn":[0.7556163596],"iteration":227,"passed_time":1.122251218,"remaining_time":1.831041461},
{"learn":[0.7554453683],"iteration":228,"passed_time":1.127681843,"remaining_time":1.826943074},
{"learn":[0.7553216972],"iteration":229,"passed_time":1.132747669,"remaining_time":1.82224625},
{"learn":[0.7551758318],"iteration":230,"passed_time":1.139670275,"remaining_time":1.820512257},
{"learn":[0.7550543949],"iteration":231,"passed_time":1.144392124,"remaining_time":1.81524268},
{"learn":[0.755037994],"iteration":232,"passed_time":1.148723114,"remaining_time":1.809362159},
{"learn":[0.754761376],"iteration":233,"passed_time":1.153384062,"remaining_time":1.804010968},
{"learn":[0.7545581673],"iteration":234,"passed_time":1.159457248,"remaining_time":1.80085913},
{"learn":[0.75436639],"iteration":235,"passed_time":1.164327392,"remaining_time":1.795826995},
{"learn":[0.7541803623],"iteration":236,"passed_time":1.168766438,"remaining_time":1.790135937},
{"learn":[0.754008473],"iteration":237,"passed_time":1.175075552,"remaining_time":1.787299789},
{"learn":[0.7537904737],"iteration":238,"passed_time":1.179906601,"remaining_time":1.782202021},
{"learn":[0.7535616045],"iteration":239,"passed_time":1.184813016,"remaining_time":1.777219524},
{"learn":[0.7533612423],"iteration":240,"passed_time":1.190798808,"remaining_time":1.773845528},
{"learn":[0.7530345379],"iteration":241,"passed_time":1.196177361,"remaining_time":1.769551634},
{"learn":[0.7528760492],"iteration":242,"passed_time":1.201343307,"remaining_time":1.764936464},
{"learn":[0.7526319334],"iteration":243,"passed_time":1.206653264,"remaining_time":1.760526893},
{"learn":[0.7525464798],"iteration":244,"passed_time":1.21077032,"remaining_time":1.754381485},
{"learn":[0.7523200885],"iteration":245,"passed_time":1.215362043,"remaining_time":1.748935623},
{"learn":[0.7520340241],"iteration":246,"passed_time":1.22043403,"remaining_time":1.744183047},
{"learn":[0.7518220629],"iteration":247,"passed_time":1.224788065,"remaining_time":1.738408866},
{"learn":[0.7516729536],"iteration":248,"passed_time":1.229206715,"remaining_time":1.732737176},
{"learn":[0.7514461794],"iteration":249,"passed_time":1.233762158,"remaining_time":1.727267021},
{"learn":[0.7512963562],"iteration":250,"passed_time":1.238570263,"remaining_time":1.722155466},
{"learn":[0.7512073604],"iteration":251,"passed_time":1.243100909,"remaining_time":1.71666316},
{"learn":[0.7510623144],"iteration":252,"passed_time":1.247737012,"remaining_time":1.711323095},
{"learn":[0.750902988],"iteration":253,"passed_time":1.252588989,"remaining_time":1.706282638},
{"learn":[0.7507847785],"iteration":254,"passed_time":1.25706943,"remaining_time":1.700740994},
{"learn":[0.7507644621],"iteration":255,"passed_time":1.261662277,"remaining_time":1.695358685},
{"learn":[0.7506380344],"iteration":256,"passed_time":1.266034388,"remaining_time":1.689687918},
{"learn":[0.7504918963],"iteration":257,"passed_time":1.270731179,"remaining_time":1.68445761},
{"learn":[0.7503021547],"iteration":258,"passed_time":1.275116215,"remaining_time":1.678820963},
{"learn":[0.7500774928],"iteration":259,"passed_time":1.279689601,"remaining_time":1.673440247},
{"learn":[0.7497915373],"iteration":260,"passed_time":1.284308222,"remaining_time":1.668124473},
{"learn":[0.7496483603],"iteration":261,"passed_time":1.288835371,"remaining_time":1.662696012},
{"learn":[0.7495019689],"iteration":262,"passed_time":1.294031044,"remaining_time":1.658131033},
{"learn":[0.7491853506],"iteration":263,"passed_time":1.300051549,"remaining_time":1.654611062},
{"learn":[0.7489097445],"iteration":264,"passed_time":1.305359773,"remaining_time":1.650171789},
{"learn":[0.7487735185],"iteration":265,"passed_time":1.31094755,"remaining_time":1.646076999},
{"learn":[0.748534061],"iteration":266,"passed_time":1.316656968,"remaining_time":1.642122736},
{"learn":[0.7481866486],"iteration":267,"passed_time":1.322670384,"remaining_time":1.638531968},
{"learn":[0.7481720662],"iteration":268,"passed_time":1.327405177,"remaining_time":1.633349865},
{"learn":[0.7480146443],"iteration":269,"passed_time":1.332088631,"remaining_time":1.628108327},
{"learn":[0.7477076823],"iteration":270,"passed_time":1.337261789,"remaining_time":1.623465419},
{"learn":[0.7475217629],"iteration":271,"passed_time":1.341787886,"remaining_time":1.618038334},
{"learn":[0.7474006111],"iteration":272,"passed_time":1.346246019,"remaining_time":1.612536441},
{"learn":[0.7471919033],"iteration":273,"passed_time":1.351282313,"remaining_time":1.607730051},
{"learn":[0.7470197822],"iteration":274,"passed_time":1.355914016,"remaining_time":1.602443837},
{"learn":[0.7468755436],"iteration":275,"passed_time":1.360472385,"remaining_time":1.597076279},
{"learn":[0.7466844147],"iteration":276,"passed_time":1.364822349,"remaining_time":1.591471547},
{"learn":[0.7465568524],"iteration":277,"passed_time":1.36960721,"remaining_time":1.586379574},
{"learn":[0.7463212555],"iteration":278,"passed_time":1.374120613,"remaining_time":1.58097748},
{"learn":[0.7460747274],"iteration":279,"passed_time":1.378598675,"remaining_time":1.575541343},
{"learn":[0.7458960593],"iteration":280,"passed_time":1.383046344,"remaining_time":1.570077522},
{"learn":[0.7457489774],"iteration":281,"passed_time":1.38759474,"remaining_time":1.564734494},
{"learn":[0.7455973875],"iteration":282,"passed_time":1.392031185,"remaining_time":1.559271681},
{"learn":[0.7453234891],"iteration":283,"passed_time":1.396612544,"remaining_time":1.553977338},
{"learn":[0.7450916275],"iteration":284,"passed_time":1.401773239,"remaining_time":1.549328317},
{"learn":[0.7448825591],"iteration":285,"passed_time":1.406447291,"remaining_time":1.544141432},
{"learn":[0.74467765],"iteration":286,"passed_time":1.411027508,"remaining_time":1.538855784},
{"learn":[0.7445299176],"iteration":287,"passed_time":1.415566676,"remaining_time":1.533530565},
{"learn":[0.7442823107],"iteration":288,"passed_time":1.420176614,"remaining_time":1.528286945},
{"learn":[0.7441698416],"iteration":289,"passed_time":1.424592267,"remaining_time":1.522840009},
{"learn":[0.7439616139],"iteration":290,"passed_time":1.429197343,"remaining_time":1.517601303},
{"learn":[0.7437450058],"iteration":291,"passed_time":1.433929898,"remaining_time":1.512501399},
{"learn":[0.7436262326],"iteration":292,"passed_time":1.438306221,"remaining_time":1.50703075},
{"learn":[0.7435283348],"iteration":293,"passed_time":1.442761163,"remaining_time":1.501649373},
{"learn":[0.743311099],"iteration":294,"passed_time":1.448020049,"remaining_time":1.497105474},
{"learn":[0.7432997514],"iteration":295,"passed_time":1.452326085,"remaining_time":1.491578141},
{"learn":[0.7430959917],"iteration":296,"passed_time":1.456894728,"remaining_time":1.486326945},
{"learn":[0.7427975969],"iteration":297,"passed_time":1.461845213,"remaining_time":1.481467296},
{"learn":[0.7426603223],"iteration":298,"passed_time":1.466774318,"remaining_time":1.476585518},
{"learn":[0.7424696273],"iteration":299,"passed_time":1.471280076,"remaining_time":1.471280076},
{"learn":[0.742079078],"iteration":300,"passed_time":1.475860757,"remaining_time":1.466054373},
{"learn":[0.7420691561],"iteration":301,"passed_time":1.479949934,"remaining_time":1.460347949},
{"learn":[0.7419062757],"iteration":302,"passed_time":1.484621368,"remaining_time":1.455222925},
{"learn":[0.7417542278],"iteration":303,"passed_time":1.489279485,"remaining_time":1.450087919},
{"learn":[0.7415067362],"iteration":304,"passed_time":1.494844593,"remaining_time":1.445833295},
{"learn":[0.7412691642],"iteration":305,"passed_time":1.500319879,"remaining_time":1.441483805},
{"learn":[0.7410651154],"iteration":306,"passed_time":1.505890066,"remaining_time":1.437217555},
{"learn":[0.7410551668],"iteration":307,"passed_time":1.51020737,"remaining_time":1.431755039},
{"learn":[0.7408693656],"iteration":308,"passed_time":1.515163476,"remaining_time":1.426901526},
{"learn":[0.7406396345],"iteration":309,"passed_time":1.520780043,"remaining_time":1.422665201},
{"learn":[0.7404984156],"iteration":310,"passed_time":1.525396657,"remaining_time":1.417490784},
{"learn":[0.7403366912],"iteration":311,"passed_time":1.530033952,"remaining_time":1.412339033},
{"learn":[0.7401676016],"iteration":312,"passed_time":1.536017937,"remaining_time":1.408425393},
{"learn":[0.7399567938],"iteration":313,"passed_time":1.540604377,"remaining_time":1.403225643},
{"learn":[0.7398452407],"iteration":314,"passed_time":1.545131841,"remaining_time":1.397976427},
{"learn":[0.7397242094],"iteration":315,"passed_time":1.550415431,"remaining_time":1.393411336},
{"learn":[0.7394177866],"iteration":316,"passed_time":1.555617106,"remaining_time":1.388768584},
{"learn":[0.7392324168],"iteration":317,"passed_time":1.560169083,"remaining_time":1.383546168},
{"learn":[0.7389818671],"iteration":318,"passed_time":1.565124913,"remaining_time":1.3786837},
{"learn":[0.7387117715],"iteration":319,"passed_time":1.569976255,"remaining_time":1.373729223},
{"learn":[0.738510501],"iteration":320,"passed_time":1.574651772,"remaining_time":1.368622568},
{"learn":[0.7382674673],"iteration":321,"passed_time":1.57926036,"remaining_time":1.363460808},
{"learn":[0.7381456642],"iteration":322,"passed_time":1.584097447,"remaining_time":1.35849843},
{"learn":[0.7379014082],"iteration":323,"passed_time":1.588777356,"remaining_time":1.353402933},
{"learn":[0.73789353],"iteration":324,"passed_time":1.593001738,"remaining_time":1.347924548},
{"learn":[0.7377275299],"iteration":325,"passed_time":1.597851696,"remaining_time":1.342979646},
{"learn":[0.7374926772],"iteration":326,"passed_time":1.603066953,"remaining_time":1.338340301},
{"learn":[0.7373798009],"iteration":327,"passed_time":1.607467595,"remaining_time":1.333021908},
{"learn":[0.7372560005],"iteration":328,"passed_time":1.611949757,"remaining_time":1.327776244},
{"learn":[0.7370765847],"iteration":329,"passed_time":1.616998859,"remaining_time":1.322999067},
{"learn":[0.7368541384],"iteration":330,"passed_time":1.621443197,"remaining_time":1.317728762},
{"learn":[0.7366243524],"iteration":331,"passed_time":1.626079214,"remaining_time":1.312618161},
{"learn":[0.7365495713],"iteration":332,"passed_time":1.630572861,"remaining_time":1.307396258},
{"learn":[0.7363734609],"iteration":333,"passed_time":1.635004343,"remaining_time":1.302129208},
{"learn":[0.7359716408],"iteration":334,"passed_time":1.639736627,"remaining_time":1.297105093},
{"learn":[0.735958987],"iteration":335,"passed_time":1.643915976,"remaining_time":1.291648267},
{"learn":[0.7357966242],"iteration":336,"passed_time":1.648549745,"remaining_time":1.286553658},
{"learn":[0.7356886258],"iteration":337,"passed_time":1.653038564,"remaining_time":1.28134942},
{"learn":[0.7355613626],"iteration":338,"passed_time":1.657499748,"remaining_time":1.276128125},
{"learn":[0.7355533975],"iteration":339,"passed_time":1.662012117,"remaining_time":1.270950443},
{"learn":[0.7353273655],"iteration":340,"passed_time":1.666475422,"remaining_time":1.265739397},
{"learn":[0.7351871264],"iteration":341,"passed_time":1.670371799,"remaining_time":1.260105041},
{"learn":[0.7350227287],"iteration":342,"passed_time":1.675066116,"remaining_time":1.255078693},
{"learn":[0.7347681104],"iteration":343,"passed_time":1.67971816,"remaining_time":1.250022817},
{"learn":[0.7347626077],"iteration":344,"passed_time":1.683839732,"remaining_time":1.244577193},
{"learn":[0.7346559418],"iteration":345,"passed_time":1.688648584,"remaining_time":1.239643758},
{"learn":[0.7344545677],"iteration":346,"passed_time":1.693246937,"remaining_time":1.234557565},
{"learn":[0.7342775208],"iteration":347,"passed_time":1.698128126,"remaining_time":1.229678988},
{"learn":[0.7341753938],"iteration":348,"passed_time":1.70256234,"remaining_time":1.224478932},
{"learn":[0.7340164982],"iteration":349,"passed_time":1.707130242,"remaining_time":1.219378744},
{"learn":[0.7339785246],"iteration":350,"passed_time":1.711616907,"remaining_time":1.214223959},
{"learn":[0.7338831885],"iteration":351,"passed_time":1.715979132,"remaining_time":1.208985297},
{"learn":[0.7337184621],"iteration":352,"passed_time":1.720850739,"remaining_time":1.204108024},
{"learn":[0.7337115311],"iteration":353,"passed_time":1.726193735,"remaining_time":1.199558358},
{"learn":[0.7335201312],"iteration":354,"passed_time":1.7314734,"remaining_time":1.194960515},
{"learn":[0.7332364933],"iteration":355,"passed_time":1.737178357,"remaining_time":1.190650334},
{"learn":[0.7331047261],"iteration":356,"passed_time":1.74273078,"remaining_time":1.186228514},
{"learn":[0.7327500419],"iteration":357,"passed_time":1.748715876,"remaining_time":1.182092854},
{"learn":[0.7325982629],"iteration":358,"passed_time":1.75460103,"remaining_time":1.1778798},
{"learn":[0.7324728051],"iteration":359,"passed_time":1.759443034,"remaining_time":1.172962022},
{"learn":[0.7322288501],"iteration":360,"passed_time":1.764233278,"remaining_time":1.168010397},
{"learn":[0.7320305147],"iteration":361,"passed_time":1.769014551,"remaining_time":1.163053765},
{"learn":[0.7318795117],"iteration":362,"passed_time":1.773591034,"remaining_time":1.157964394},
{"learn":[0.7317019197],"iteration":363,"passed_time":1.778454746,"remaining_time":1.153064066},
{"learn":[0.7315345363],"iteration":364,"passed_time":1.783135732,"remaining_time":1.148046293},
{"learn":[0.7313292666],"iteration":365,"passed_time":1.787641542,"remaining_time":1.142918363},
{"learn":[0.7311774046],"iteration":366,"passed_time":1.792264424,"remaining_time":1.137868149},
{"learn":[0.7309314304],"iteration":367,"passed_time":1.79736519,"remaining_time":1.133121533},
{"learn":[0.7309227449],"iteration":368,"passed_time":1.801414933,"remaining_time":1.12771504},
{"learn":[0.7307198821],"iteration":369,"passed_time":1.805894774,"remaining_time":1.122583238},
{"learn":[0.7305753562],"iteration":370,"passed_time":1.810839675,"remaining_time":1.117742009},
{"learn":[0.7303704338],"iteration":371,"passed_time":1.816051625,"remaining_time":1.113063899},
{"learn":[0.7301009702],"iteration":372,"passed_time":1.82111957,"remaining_time":1.108295288},
{"learn":[0.7297563232],"iteration":373,"passed_time":1.826362651,"remaining_time":1.103630906},
{"learn":[0.7296083894],"iteration":374,"passed_time":1.831516704,"remaining_time":1.098910023},
{"learn":[0.7294650319],"iteration":375,"passed_time":1.836137117,"remaining_time":1.093868921},
{"learn":[0.729328881],"iteration":376,"passed_time":1.840743764,"remaining_time":1.088821908},
{"learn":[0.7291906275],"iteration":377,"passed_time":1.845903481,"remaining_time":1.084102045},
{"learn":[0.7290823652],"iteration":378,"passed_time":1.851047275,"remaining_time":1.079370575},
{"learn":[0.7288818119],"iteration":379,"passed_time":1.856680907,"remaining_time":1.074920525},
{"learn":[0.7286568897],"iteration":380,"passed_time":1.86216291,"remaining_time":1.070377106},
{"learn":[0.7285546047],"iteration":381,"passed_time":1.866611599,"remaining_time":1.06523908},
{"learn":[0.7283951518],"iteration":382,"passed_time":1.871149506,"remaining_time":1.060155203},
{"learn":[0.728110927],"iteration":383,"passed_time":1.877591051,"remaining_time":1.056144966},
{"learn":[0.7278833123],"iteration":384,"passed_time":1.882752688,"remaining_time":1.051407345},
{"learn":[0.7276862204],"iteration":385,"passed_time":1.887655474,"remaining_time":1.046524019},
{"learn":[0.7275043316],"iteration":386,"passed_time":1.893261142,"remaining_time":1.04202745},
{"learn":[0.7274349898],"iteration":387,"passed_time":1.898667271,"remaining_time":1.037416138},
{"learn":[0.7272886827],"iteration":388,"passed_time":1.903963317,"remaining_time":1.032741028},
{"learn":[0.7271680638],"iteration":389,"passed_time":1.909333649,"remaining_time":1.028102734},
{"learn":[0.7270366946],"iteration":390,"passed_time":1.914347976,"remaining_time":1.023270401},
{"learn":[0.7268517602],"iteration":391,"passed_time":1.919202559,"remaining_time":1.018352378},
{"learn":[0.7266845684],"iteration":392,"passed_time":1.9238184,"remaining_time":1.013308928},
{"learn":[0.7265496672],"iteration":393,"passed_time":1.928605732,"remaining_time":1.008357312},
{"learn":[0.7264148254],"iteration":394,"passed_time":1.933162161,"remaining_time":1.003286691},
{"learn":[0.7262955375],"iteration":395,"passed_time":1.938055614,"remaining_time":0.9983922862},
{"learn":[0.7261499107],"iteration":396,"passed_time":1.942685129,"remaining_time":0.9933629249},
{"learn":[0.726024594],"iteration":397,"passed_time":1.947148114,"remaining_time":0.9882510527},
{"learn":[0.7258856952],"iteration":398,"passed_time":1.951603164,"remaining_time":0.9831384359},
{"learn":[0.7257247256],"iteration":399,"passed_time":1.956101602,"remaining_time":0.9780508008},
{"learn":[0.7255144258],"iteration":400,"passed_time":1.960938726,"remaining_time":0.9731341808},
{"learn":[0.7254168181],"iteration":401,"passed_time":1.965511238,"remaining_time":0.9680876248},
{"learn":[0.7251194993],"iteration":402,"passed_time":1.969978294,"remaining_time":0.962991871},
{"learn":[0.7248922395],"iteration":403,"passed_time":1.974821999,"remaining_time":0.9580819597},
{"learn":[0.7247692567],"iteration":404,"passed_time":1.980029386,"remaining_time":0.9533474822},
{"learn":[0.7246506118],"iteration":405,"passed_time":1.984385412,"remaining_time":0.9482038666},
{"learn":[0.7243920791],"iteration":406,"passed_time":1.989049302,"remaining_time":0.9432101111},
{"learn":[0.7242270411],"iteration":407,"passed_time":1.993690133,"remaining_time":0.9382071212},
{"learn":[0.7240538196],"iteration":408,"passed_time":1.998277993,"remaining_time":0.9331811655},
{"learn":[0.7238838582],"iteration":409,"passed_time":2.002892503,"remaining_time":0.9281696967},
{"learn":[0.7236236649],"iteration":410,"passed_time":2.007894737,"remaining_time":0.9233384556},
{"learn":[0.7234688368],"iteration":411,"passed_time":2.012546385,"remaining_time":0.9183464089},
{"learn":[0.723398931],"iteration":412,"passed_time":2.017008,"remaining_time":0.9132699659},
{"learn":[0.7232038753],"iteration":413,"passed_time":2.021418805,"remaining_time":0.9081736661},
{"learn":[0.7230410211],"iteration":414,"passed_time":2.026829837,"remaining_time":0.903526554},
{"learn":[0.7230059217],"iteration":415,"passed_time":2.032525373,"remaining_time":0.8990016075},
{"learn":[0.722921226],"iteration":416,"passed_time":2.038301809,"remaining_time":0.8945065494},
{"learn":[0.7227435399],"iteration":417,"passed_time":2.043328825,"remaining_time":0.889679058},
{"learn":[0.7225666306],"iteration":418,"passed_time":2.047801898,"remaining_time":0.884611321},
{"learn":[0.7223928263],"iteration":419,"passed_time":2.052847527,"remaining_time":0.8797917974},
{"learn":[0.722251356],"iteration":420,"passed_time":2.058162423,"remaining_time":0.8750856857},
{"learn":[0.7221415729],"iteration":421,"passed_time":2.063406265,"remaining_time":0.8703467183},
{"learn":[0.721781912],"iteration":422,"passed_time":2.068876996,"remaining_time":0.8657003032},
{"learn":[0.7216650878],"iteration":423,"passed_time":2.073944994,"remaining_time":0.8608828276},
{"learn":[0.7214777222],"iteration":424,"passed_time":2.078476394,"remaining_time":0.8558432209},
{"learn":[0.7214287069],"iteration":425,"passed_time":2.082763114,"remaining_time":0.8507060605},
{"learn":[0.7212696094],"iteration":426,"passed_time":2.087593584,"remaining_time":0.8457931852},
{"learn":[0.7211093553],"iteration":427,"passed_time":2.092542856,"remaining_time":0.8409284374},
{"learn":[0.7210992669],"iteration":428,"passed_time":2.096728609,"remaining_time":0.8357589561},
{"learn":[0.7209487151],"iteration":429,"passed_time":2.101172847,"remaining_time":0.8306962418},
{"learn":[0.7207323947],"iteration":430,"passed_time":2.106099583,"remaining_time":0.8258255904},
{"learn":[0.7205425722],"iteration":431,"passed_time":2.110837338,"remaining_time":0.820881187},
{"learn":[0.7202304644],"iteration":432,"passed_time":2.115508699,"remaining_time":0.8159121311},
{"learn":[0.7200491151],"iteration":433,"passed_time":2.120200015,"remaining_time":0.8109520793},
{"learn":[0.7198655465],"iteration":434,"passed_time":2.125010439,"remaining_time":0.8060384426},
{"learn":[0.719713022],"iteration":435,"passed_time":2.129454027,"remaining_time":0.8009872946},
{"learn":[0.7194707382],"iteration":436,"passed_time":2.134319038,"remaining_time":0.7960961171},
{"learn":[0.7192972723],"iteration":437,"passed_time":2.139028313,"remaining_time":0.7911474582},
{"learn":[0.719186058],"iteration":438,"passed_time":2.143443731,"remaining_time":0.7860921202},
{"learn":[0.7191063008],"iteration":439,"passed_time":2.148050469,"remaining_time":0.7811092614},
{"learn":[0.7189376968],"iteration":440,"passed_time":2.153424406,"remaining_time":0.7764047178},
{"learn":[0.7187378314],"iteration":441,"passed_time":2.159018505,"remaining_time":0.7717758457},
{"learn":[0.7185720939],"iteration":442,"passed_time":2.164741022,"remaining_time":0.7671881275},
{"learn":[0.7184436631],"iteration":443,"passed_time":2.169862097,"remaining_time":0.76238398},
{"learn":[0.7182797149],"iteration":444,"passed_time":2.175673174,"remaining_time":0.7578187459},
{"learn":[0.7181433747],"iteration":445,"passed_time":2.181484535,"remaining_time":0.7532480234},
{"learn":[0.7180186729],"iteration":446,"passed_time":2.186772309,"remaining_time":0.7484925354},
{"learn":[0.7178453768],"iteration":447,"passed_time":2.191859524,"remaining_time":0.7436666243},
{"learn":[0.7177272082],"iteration":448,"passed_time":2.197271008,"remaining_time":0.7389486017},
{"learn":[0.7175661357],"iteration":449,"passed_time":2.202470661,"remaining_time":0.734156887},
{"learn":[0.7173782725],"iteration":450,"passed_time":2.208947561,"remaining_time":0.729785336},
{"learn":[0.7171711889],"iteration":451,"passed_time":2.213643814,"remaining_time":0.7248214257},
{"learn":[0.7168942713],"iteration":452,"passed_time":2.218361041,"remaining_time":0.7198655035},
{"learn":[0.7167637775],"iteration":453,"passed_time":2.223819858,"remaining_time":0.7151491174},
{"learn":[0.7166801073],"iteration":454,"passed_time":2.228852653,"remaining_time":0.7102937027},
{"learn":[0.7165067184],"iteration":455,"passed_time":2.233706629,"remaining_time":0.7053810409},
{"learn":[0.7163653916],"iteration":456,"passed_time":2.239374606,"remaining_time":0.7007233448},
{"learn":[0.7161768737],"iteration":457,"passed_time":2.244774884,"remaining_time":0.695978239},
{"learn":[0.7159369195],"iteration":458,"passed_time":2.249460473,"remaining_time":0.6910107335},
{"learn":[0.7157434271],"iteration":459,"passed_time":2.254445439,"remaining_time":0.6861355683},
{"learn":[0.7156338574],"iteration":460,"passed_time":2.259570443,"remaining_time":0.6813021509},
{"learn":[0.7153894411],"iteration":461,"passed_time":2.264320283,"remaining_time":0.6763554092},
{"learn":[0.7150822949],"iteration":462,"passed_time":2.26906831,"remaining_time":0.6714089815},
{"learn":[0.7148571577],"iteration":463,"passed_time":2.274221123,"remaining_time":0.6665820532},
{"learn":[0.7146516613],"iteration":464,"passed_time":2.278929717,"remaining_time":0.6616247566},
{"learn":[0.7145277086],"iteration":465,"passed_time":2.283671339,"remaining_time":0.6566780244},
{"learn":[0.7143407842],"iteration":466,"passed_time":2.290410021,"remaining_time":0.6523009268},
{"learn":[0.7141606378],"iteration":467,"passed_time":2.29604172,"remaining_time":0.6476015107},
{"learn":[0.7140831071],"iteration":468,"passed_time":2.301282872,"remaining_time":0.6427890324},
{"learn":[0.7138943255],"iteration":469,"passed_time":2.306470342,"remaining_time":0.6379598818},
{"learn":[0.713687847],"iteration":470,"passed_time":2.311300533,"remaining_time":0.6330313561},
{"learn":[0.7135648477],"iteration":471,"passed_time":2.315784555,"remaining_time":0.6280093709},
{"learn":[0.7134325391],"iteration":472,"passed_time":2.321053526,"remaining_time":0.6232004183},
{"learn":[0.7133510257],"iteration":473,"passed_time":2.325572699,"remaining_time":0.6181902111},
{"learn":[0.7132885589],"iteration":474,"passed_time":2.329990317,"remaining_time":0.6131553465},
{"learn":[0.713148142],"iteration":475,"passed_time":2.33460423,"remaining_time":0.6081742111},
{"learn":[0.7129676326],"iteration":476,"passed_time":2.339570059,"remaining_time":0.603285361},
{"learn":[0.7127004642],"iteration":477,"passed_time":2.344180353,"remaining_time":0.5983054456},
{"learn":[0.7126128125],"iteration":478,"passed_time":2.348717349,"remaining_time":0.5933085579},
{"learn":[0.7124092182],"iteration":479,"passed_time":2.353659974,"remaining_time":0.5884149934},
{"learn":[0.7122243513],"iteration":480,"passed_time":2.358212691,"remaining_time":0.5834247614},
{"learn":[0.7120674163],"iteration":481,"passed_time":2.362940178,"remaining_time":0.5784791308},
{"learn":[0.7119590578],"iteration":482,"passed_time":2.367333007,"remaining_time":0.5734533372},
{"learn":[0.7117617925],"iteration":483,"passed_time":2.372184425,"remaining_time":0.5685400688},
{"learn":[0.7115831791],"iteration":484,"passed_time":2.376855036,"remaining_time":0.5635841837},
{"learn":[0.7114070479],"iteration":485,"passed_time":2.381664847,"remaining_time":0.5586621247},
{"learn":[0.711276054],"iteration":486,"passed_time":2.386520485,"remaining_time":0.5537511597},
{"learn":[0.7112153776],"iteration":487,"passed_time":2.390918736,"remaining_time":0.5487354476},
{"learn":[0.7110854215],"iteration":488,"passed_time":2.395824578,"remaining_time":0.5438374809},
{"learn":[0.7109001354],"iteration":489,"passed_time":2.40025186,"remaining_time":0.5388320501},
{"learn":[0.7107647416],"iteration":490,"passed_time":2.404886613,"remaining_time":0.5338750323},
{"learn":[0.7105105325],"iteration":491,"passed_time":2.409737289,"remaining_time":0.5289667219},
{"learn":[0.7102890376],"iteration":492,"passed_time":2.414410941,"remaining_time":0.5240202246},
{"learn":[0.7101275932],"iteration":493,"passed_time":2.419054613,"remaining_time":0.5190683987},
{"learn":[0.7099883335],"iteration":494,"passed_time":2.423766858,"remaining_time":0.5141323638},
{"learn":[0.7098188861],"iteration":495,"passed_time":2.428415799,"remaining_time":0.5091839578},
{"learn":[0.7096735753],"iteration":496,"passed_time":2.433026248,"remaining_time":0.5042287797},
{"learn":[0.7094164969],"iteration":497,"passed_time":2.438209864,"remaining_time":0.4993923818},
{"learn":[0.7093351668],"iteration":498,"passed_time":2.443490804,"remaining_time":0.4945742909},
{"learn":[0.7091896654],"iteration":499,"passed_time":2.448533635,"remaining_time":0.4897067271},
{"learn":[0.7090209399],"iteration":500,"passed_time":2.454004599,"remaining_time":0.4849230645},
{"learn":[0.7088447045],"iteration":501,"passed_time":2.458794339,"remaining_time":0.4800036757},
{"learn":[0.7086783868],"iteration":502,"passed_time":2.463240658,"remaining_time":0.4750185761},
{"learn":[0.7085106866],"iteration":503,"passed_time":2.468176663,"remaining_time":0.4701288881},
{"learn":[0.7084155552],"iteration":504,"passed_time":2.473144812,"remaining_time":0.4652450637},
{"learn":[0.7082404099],"iteration":505,"passed_time":2.477600274,"remaining_time":0.4602656636},
{"learn":[0.7081388798],"iteration":506,"passed_time":2.482106095,"remaining_time":0.4552975677},
{"learn":[0.7079978343],"iteration":507,"passed_time":2.487670485,"remaining_time":0.4505230012},
{"learn":[0.7078464301],"iteration":508,"passed_time":2.493839025,"remaining_time":0.4458533424},
{"learn":[0.7076990763],"iteration":509,"passed_time":2.498555063,"remaining_time":0.4409214817},
{"learn":[0.7075520377],"iteration":510,"passed_time":2.503658151,"remaining_time":0.4360578775},
{"learn":[0.707421218],"iteration":511,"passed_time":2.508358073,"remaining_time":0.4311240439},
{"learn":[0.7072702103],"iteration":512,"passed_time":2.512951346,"remaining_time":0.4261730353},
{"learn":[0.7069801467],"iteration":513,"passed_time":2.518031547,"remaining_time":0.4213048891},
{"learn":[0.7068395806],"iteration":514,"passed_time":2.5228179,"remaining_time":0.4163874204},
{"learn":[0.7067302282],"iteration":515,"passed_time":2.527509568,"remaining_time":0.411455046},
{"learn":[0.7065587053],"iteration":516,"passed_time":2.532368732,"remaining_time":0.4065504928},
{"learn":[0.7064427165],"iteration":517,"passed_time":2.536911316,"remaining_time":0.4015959999},
{"learn":[0.7062909522],"iteration":518,"passed_time":2.541580106,"remaining_time":0.3966627912},
{"learn":[0.7060905401],"iteration":519,"passed_time":2.546317382,"remaining_time":0.3917411357},
{"learn":[0.7058686467],"iteration":520,"passed_time":2.552523228,"remaining_time":0.3870428695},
{"learn":[0.7056823677],"iteration":521,"passed_time":2.557514406,"remaining_time":0.382157325},
{"learn":[0.7054902782],"iteration":522,"passed_time":2.56252678,"remaining_time":0.3772744972},
{"learn":[0.705350681],"iteration":523,"passed_time":2.567759972,"remaining_time":0.372423202},
{"learn":[0.7052375431],"iteration":524,"passed_time":2.572488538,"remaining_time":0.3674983625},
{"learn":[0.7050986612],"iteration":525,"passed_time":2.577409491,"remaining_time":0.3626013352},
{"learn":[0.7050118829],"iteration":526,"passed_time":2.584383797,"remaining_time":0.3579886474},
{"learn":[0.7047607754],"iteration":527,"passed_time":2.590380757,"remaining_time":0.3532337396},
{"learn":[0.7045793064],"iteration":528,"passed_time":2.597026518,"remaining_time":0.348561215},
{"learn":[0.7044341162],"iteration":529,"passed_time":2.604270885,"remaining_time":0.3439603056},
{"learn":[0.7042481544],"iteration":530,"passed_time":2.611328396,"remaining_time":0.3393251587},
{"learn":[0.7041091628],"iteration":531,"passed_time":2.618479626,"remaining_time":0.3346928845},
{"learn":[0.7038982494],"iteration":532,"passed_time":2.625826196,"remaining_time":0.3300757132},
{"learn":[0.7037618485],"iteration":533,"passed_time":2.632356042,"remaining_time":0.325347376},
{"learn":[0.7036688429],"iteration":534,"passed_time":2.638366795,"remaining_time":0.3205492368},
{"learn":[0.703524573],"iteration":535,"passed_time":2.644043819,"remaining_time":0.3157067247},
{"learn":[0.7033787921],"iteration":536,"passed_time":2.649116858,"remaining_time":0.3107902459},
{"learn":[0.7033139782],"iteration":537,"passed_time":2.653687512,"remaining_time":0.3058152895},
{"learn":[0.7031227697],"iteration":538,"passed_time":2.658945798,"remaining_time":0.3009196543},
{"learn":[0.7029325764],"iteration":539,"passed_time":2.663857414,"remaining_time":0.2959841571},
{"learn":[0.7026715266],"iteration":540,"passed_time":2.668735434,"remaining_time":0.2910450843},
{"learn":[0.7024484936],"iteration":541,"passed_time":2.673405573,"remaining_time":0.2860839912},
{"learn":[0.7023715514],"iteration":542,"passed_time":2.677821991,"remaining_time":0.2810973361},
{"learn":[0.702163311],"iteration":543,"passed_time":2.682877894,"remaining_time":0.2761786067},
{"learn":[0.7020345793],"iteration":544,"passed_time":2.687708608,"remaining_time":0.2712366485},
{"learn":[0.701877882],"iteration":545,"passed_time":2.692146559,"remaining_time":0.2662562531},
{"learn":[0.7016967477],"iteration":546,"passed_time":2.696998001,"remaining_time":0.261317905},
{"learn":[0.7015925432],"iteration":547,"passed_time":2.701645552,"remaining_time":0.2563605268},
{"learn":[0.7014432729],"iteration":548,"passed_time":2.706227691,"remaining_time":0.2513982008},
{"learn":[0.7014387682],"iteration":549,"passed_time":2.710453504,"remaining_time":0.246404864},
{"learn":[0.7013415375],"iteration":550,"passed_time":2.71508676,"remaining_time":0.2414505467},
{"learn":[0.7011238424],"iteration":551,"passed_time":2.719658905,"remaining_time":0.2364920787},
{"learn":[0.7010008162],"iteration":552,"passed_time":2.724112276,"remaining_time":0.2315249132},
{"learn":[0.7008770547],"iteration":553,"passed_time":2.728658977,"remaining_time":0.2265673519},
{"learn":[0.700748342],"iteration":554,"passed_time":2.733251039,"remaining_time":0.2216149491},
{"learn":[0.7006804193],"iteration":555,"passed_time":2.737589338,"remaining_time":0.2166437605},
{"learn":[0.7004746033],"iteration":556,"passed_time":2.742201217,"remaining_time":0.2116959647},
{"learn":[0.7002751157],"iteration":557,"passed_time":2.747412797,"remaining_time":0.2067945116},
{"learn":[0.7000739756],"iteration":558,"passed_time":2.751968376,"remaining_time":0.2018438344},
{"learn":[0.6998869813],"iteration":559,"passed_time":2.756606825,"remaining_time":0.1969004875},
{"learn":[0.6997128957],"iteration":560,"passed_time":2.761207695,"remaining_time":0.1919556152},
{"learn":[0.6995408147],"iteration":561,"passed_time":2.765983024,"remaining_time":0.1870237632},
{"learn":[0.6994175468],"iteration":562,"passed_time":2.770644381,"remaining_time":0.1820849771},
{"learn":[0.699253056],"iteration":563,"passed_time":2.775428424,"remaining_time":0.1771550058},
{"learn":[0.6990565491],"iteration":564,"passed_time":2.780282372,"remaining_time":0.1722298814},
{"learn":[0.6988944641],"iteration":565,"passed_time":2.785010303,"remaining_time":0.1672974387},
{"learn":[0.6987610876],"iteration":566,"passed_time":2.789514443,"remaining_time":0.1623526925},
{"learn":[0.6986280732],"iteration":567,"passed_time":2.793997665,"remaining_time":0.1574083192},
{"learn":[0.6984814847],"iteration":568,"passed_time":2.798670667,"remaining_time":0.1524759063},
{"learn":[0.6983086705],"iteration":569,"passed_time":2.803239921,"remaining_time":0.1475389432},
{"learn":[0.6981670798],"iteration":570,"passed_time":2.808037618,"remaining_time":0.1426148703},
{"learn":[0.6980184608],"iteration":571,"passed_time":2.812757457,"remaining_time":0.137687428},
{"learn":[0.6979978547],"iteration":572,"passed_time":2.816812162,"remaining_time":0.1327293689},
{"learn":[0.6978728656],"iteration":573,"passed_time":2.821434695,"remaining_time":0.1278001778},
{"learn":[0.6977717853],"iteration":574,"passed_time":2.826178168,"remaining_time":0.1228773116},
{"learn":[0.6975944088],"iteration":575,"passed_time":2.830988964,"remaining_time":0.1179578735},
{"learn":[0.6974819972],"iteration":576,"passed_time":2.835574975,"remaining_time":0.1130298517},
{"learn":[0.6973290879],"iteration":577,"passed_time":2.840151561,"remaining_time":0.1081026546},
{"learn":[0.6972289899],"iteration":578,"passed_time":2.844582798,"remaining_time":0.1031713968},
{"learn":[0.6970404916],"iteration":579,"passed_time":2.849167597,"remaining_time":0.09824715853},
{"learn":[0.6969122349],"iteration":580,"passed_time":2.853991019,"remaining_time":0.0933318922},
{"learn":[0.6968516316],"iteration":581,"passed_time":2.858446017,"remaining_time":0.08840554691},
{"learn":[0.6967145423],"iteration":582,"passed_time":2.863088291,"remaining_time":0.08348627951},
{"learn":[0.6966102884],"iteration":583,"passed_time":2.867172217,"remaining_time":0.07855266349},
{"learn":[0.6965182983],"iteration":584,"passed_time":2.872006168,"remaining_time":0.07364118379},
{"learn":[0.6963667918],"iteration":585,"passed_time":2.876633373,"remaining_time":0.06872502938},
{"learn":[0.6962756147],"iteration":586,"passed_time":2.881101875,"remaining_time":0.06380634475},
{"learn":[0.6961740987],"iteration":587,"passed_time":2.886101771,"remaining_time":0.05890003614},
{"learn":[0.6961285975],"iteration":588,"passed_time":2.889962986,"remaining_time":0.05397214406},
{"learn":[0.6961127963],"iteration":589,"passed_time":2.894362807,"remaining_time":0.04905699672},
{"learn":[0.6959739606],"iteration":590,"passed_time":2.898776483,"remaining_time":0.04414380432},
{"learn":[0.6958549004],"iteration":591,"passed_time":2.90381473,"remaining_time":0.03924073959},
{"learn":[0.6957444023],"iteration":592,"passed_time":2.908824952,"remaining_time":0.03433688814},
{"learn":[0.6956015636],"iteration":593,"passed_time":2.915106686,"remaining_time":0.02944552208},
{"learn":[0.6954319387],"iteration":594,"passed_time":2.91967666,"remaining_time":0.02453509798},
{"learn":[0.6953197414],"iteration":595,"passed_time":2.924197596,"remaining_time":0.01962548722},
{"learn":[0.6952368205],"iteration":596,"passed_time":2.929404783,"remaining_time":0.01472062705},
{"learn":[0.695106909],"iteration":597,"passed_time":2.934184875,"remaining_time":0.009813327341},
{"learn":[0.6949275125],"iteration":598,"passed_time":2.938743705,"remaining_time":0.00490608298},
{"learn":[0.6948336284],"iteration":599,"passed_time":2.94370288,"remaining_time":0}
]}